[
    {
        "brand": "Samsung",
        "model": "POWER BANK WIRELESS 10",
        "storage": "N/A",
        "price": 429.0,
        "platform": "electroplanet",
        "original_name": "SAMSUNG POWER BANK WIRELESS 10...",
        "timestamp": "2026-03-28T23:35:21.428742"
    },
    {
        "brand": "Samsung",
        "model": "SMARTPHONE GALAXY A07",
        "storage": "N/A",
        "price": 1249.0,
        "platform": "electroplanet",
        "original_name": "SAMSUNG SMARTPHONE GALAXY A07 ...",
        "timestamp": "2026-03-28T23:35:22.958065"
    },
    {
        "brand": "Samsung",
        "model": "BARRE DE SON HWB400F",
        "storage": "N/A",
        "price": 1399.0,
        "platform": "electroplanet",
        "original_name": "SAMSUNG BARRE DE SON HW-B400F/...",
        "timestamp": "2026-03-28T23:35:21.586515"
    },
    {
        "brand": "Samsung",
        "model": "SMARTPHONE GALAXY A07",
        "storage": "N/A",
        "price": 1490.0,
        "platform": "electroplanet",
        "original_name": "SAMSUNG SMARTPHONE GALAXY A07 ...",
        "timestamp": "2026-03-28T23:35:22.730687"
    },
    {
        "brand": "Samsung",
        "model": "TAB A11 87",
        "storage": "4GB",
        "price": 1749.0,
        "platform": "electroplanet",
        "original_name": "SAMSUNG TAB A11 (8,7) 4GB/64GB...",
        "timestamp": "2026-03-28T23:35:22.177237"
    },
    {
        "brand": "Samsung",
        "model": "SMART GALAXY A17",
        "storage": "N/A",
        "price": 1990.0,
        "platform": "electroplanet",
        "original_name": "SAMSUNG SMART GALAXY A17 (5G) ...",
        "timestamp": "2026-03-28T23:35:21.710244"
    },
    {
        "brand": "Samsung",
        "model": "SMARTPHONE GALAXY A17",
        "storage": "N/A",
        "price": 1990.0,
        "platform": "electroplanet",
        "original_name": "SAMSUNG SMARTPHONE GALAXY A17 ...",
        "timestamp": "2026-03-28T23:35:22.668536"
    },
    {
        "brand": "Samsung",
        "model": "BARRE DE SON HWB450F",
        "storage": "N/A",
        "price": 2099.0,
        "platform": "electroplanet",
        "original_name": "SAMSUNG BARRE DE SON HW-B450F/...",
        "timestamp": "2026-03-28T23:35:21.626798"
    },
    {
        "brand": "Samsung",
        "model": "TAB A11 87 128G",
        "storage": "8GB",
        "price": 2249.0,
        "platform": "electroplanet",
        "original_name": "SAMSUNG TAB A11 (8,7) 8GB/128G...",
        "timestamp": "2026-03-28T23:35:22.095266"
    },
    {
        "brand": "Samsung",
        "model": "SMARTPHONE GALAXY A17",
        "storage": "N/A",
        "price": 2490.0,
        "platform": "electroplanet",
        "original_name": "SAMSUNG SMARTPHONE GALAXY A17 ...",
        "timestamp": "2026-03-28T23:35:22.635771"
    },
    {
        "brand": "Samsung",
        "model": "SMART GALAXY A17",
        "storage": "N/A",
        "price": 2990.0,
        "platform": "electroplanet",
        "original_name": "SAMSUNG SMART GALAXY A17 (5G) ...",
        "timestamp": "2026-03-28T23:35:21.748534"
    },
    {
        "brand": "Samsung",
        "model": "Glass Fumée pour  Galaxy A56  Incassable meilleur Qualité",
        "storage": "N/A",
        "price": 4500.0,
        "platform": "jumia",
        "original_name": "Glass Fumée pour samsung Galaxy A56 5G Incassable meilleur Qualité",
        "timestamp": "2026-03-28T23:34:50.578870"
    },
    {
        "brand": "Samsung",
        "model": "PROJECTEUR FREESTYLE G",
        "storage": "N/A",
        "price": 5399.0,
        "platform": "electroplanet",
        "original_name": "SAMSUNG PROJECTEUR FREESTYLE G...",
        "timestamp": "2026-03-28T23:35:21.663832"
    },
    {
        "brand": "Samsung",
        "model": "Vidvie Écouteurs doriginal HS604 et micro pour iPhone iPad  et autres smartphones",
        "storage": "N/A",
        "price": 5500.0,
        "platform": "jumia",
        "original_name": "Vidvie Écouteurs d'original HS604 et micro pour iPhone, iPad, Samsung et autres smartphones",
        "timestamp": "2026-03-28T23:34:49.504470"
    },
    {
        "brand": "Samsung",
        "model": "MAL WW90DG5U34ABMF 9KG",
        "storage": "N/A",
        "price": 5799.0,
        "platform": "electroplanet",
        "original_name": "SAMSUNG MAL WW90DG5U34ABMF 9KG...",
        "timestamp": "2026-03-28T23:35:22.767116"
    },
    {
        "brand": "Samsung",
        "model": "MAL WW90DG6U34LXMF SIL",
        "storage": "N/A",
        "price": 5799.0,
        "platform": "electroplanet",
        "original_name": "SAMSUNG MAL WW90DG6U34LXMF SIL...",
        "timestamp": "2026-03-28T23:35:22.806803"
    },
    {
        "brand": "Samsung",
        "model": "QLED QA55Q6FAAUXMV",
        "storage": "N/A",
        "price": 6399.0,
        "platform": "electroplanet",
        "original_name": "SAMSUNG QLED QA55Q6FAAUXMV SAMSUNG",
        "timestamp": "2026-03-28T23:35:21.962854"
    },
    {
        "brand": "Samsung",
        "model": "SMARTGALAXY S25FE 8G2",
        "storage": "N/A",
        "price": 6990.0,
        "platform": "electroplanet",
        "original_name": "SAMSUNG SMARTGALAXY S25FE 8G/2...",
        "timestamp": "2026-03-28T23:35:22.441753"
    },
    {
        "brand": "Samsung",
        "model": "SMART GALAXY S25FE 8G",
        "storage": "N/A",
        "price": 6990.0,
        "platform": "electroplanet",
        "original_name": "SAMSUNG SMART GALAXY S25FE 8G/...",
        "timestamp": "2026-03-28T23:35:22.512254"
    },
    {
        "brand": "Samsung",
        "model": "LED UA75U8000FUXMV",
        "storage": "N/A",
        "price": 10699.0,
        "platform": "electroplanet",
        "original_name": "SAMSUNG LED UA75U8000FUXMV SAMSUNG",
        "timestamp": "2026-03-28T23:35:22.004448"
    },
    {
        "brand": "Samsung",
        "model": "BARRE DE SON HWQ930F",
        "storage": "N/A",
        "price": 10990.0,
        "platform": "electroplanet",
        "original_name": "SAMSUNG BARRE DE SON HW-Q930F/...",
        "timestamp": "2026-03-28T23:35:23.279651"
    },
    {
        "brand": "Iphone",
        "model": "VR Box 2Ps Casque Réalité Virtuelle  Casque VR Compatible avec   Android Lunettes Casque Réalité Virtuelle 3D",
        "storage": "N/A",
        "price": 11899.0,
        "platform": "jumia",
        "original_name": "VR Box 2Ps Casque Réalité Virtuelle - Casque VR Compatible avec iPhone & Android, Lunettes Casque Réalité Virtuelle 3D",
        "timestamp": "2026-03-28T23:35:34.395354"
    },
    {
        "brand": "Samsung",
        "model": "GALAXY S26 12+ CO",
        "storage": "512GB",
        "price": 11990.0,
        "platform": "electroplanet",
        "original_name": "SAMSUNG GALAXY S26 12+512GB CO...",
        "timestamp": "2026-03-28T23:35:21.542719"
    },
    {
        "brand": "Iphone",
        "model": "APPLE  15   MTP03",
        "storage": "128GB",
        "price": 11999.0,
        "platform": "electroplanet",
        "original_name": "APPLE IPHONE 15 128GB BLACK MTP03",
        "timestamp": "2026-03-28T23:36:02.302721"
    },
    {
        "brand": "Samsung",
        "model": "PACK REF RT47CG6422S9M",
        "storage": "N/A",
        "price": 12799.0,
        "platform": "electroplanet",
        "original_name": "SAMSUNG PACK REF RT47CG6422S9M...",
        "timestamp": "2026-03-28T23:35:22.044454"
    },
    {
        "brand": "Iphone",
        "model": "APPLE  16  ULTRAM",
        "storage": "128GB",
        "price": 13399.0,
        "platform": "electroplanet",
        "original_name": "APPLE IPHONE 16 128GB ULTRAM...",
        "timestamp": "2026-03-28T23:36:02.103976"
    },
    {
        "brand": "Iphone",
        "model": "APPLE  16",
        "storage": "128GB",
        "price": 13399.0,
        "platform": "electroplanet",
        "original_name": "APPLE IPHONE 16 128GB BLACK ...",
        "timestamp": "2026-03-28T23:36:02.153505"
    },
    {
        "brand": "Iphone",
        "model": "APPLE  15  MTP63",
        "storage": "256GB",
        "price": 13799.0,
        "platform": "electroplanet",
        "original_name": "APPLE IPHONE 15 256GB BLACKMTP63",
        "timestamp": "2026-03-28T23:36:02.257410"
    },
    {
        "brand": "Samsung",
        "model": "GALAXY S26PLUS 12+512G",
        "storage": "N/A",
        "price": 13990.0,
        "platform": "electroplanet",
        "original_name": "SAMSUNG GALAXY S26PLUS 12+512G...",
        "timestamp": "2026-03-28T23:35:21.500145"
    },
    {
        "brand": "Iphone",
        "model": "Double Microphone sans fil 2en1  Micro    USB C  Micro Cravate Sans Fil Type C    F152",
        "storage": "N/A",
        "price": 15000.0,
        "platform": "jumia",
        "original_name": "Double Microphone sans fil 2en1 , Micro iphone  / USB C , Micro Cravate Sans Fil Type C / iphone - F15-2",
        "timestamp": "2026-03-28T23:35:33.028186"
    },
    {
        "brand": "Iphone",
        "model": "APPLE  16",
        "storage": "256GB",
        "price": 15259.0,
        "platform": "electroplanet",
        "original_name": "APPLE IPHONE 16 256GB BLACK ...",
        "timestamp": "2026-03-28T23:36:02.060713"
    },
    {
        "brand": "Iphone",
        "model": "Double Microphone sans fil F152 Lavalier Lightning  et Typec 20 mètres  1 récepteur + 2 émetteurs  pour  et Android",
        "storage": "N/A",
        "price": 15900.0,
        "platform": "jumia",
        "original_name": "Double Microphone sans fil F15-2 Lavalier Lightning iPhone et Type-c 20 mètres ( 1 récepteur + 2 émetteurs ) pour iPhone et Android",
        "timestamp": "2026-03-28T23:35:33.029074"
    },
    {
        "brand": "Samsung",
        "model": "GALAXY S26ULTRA 12+512",
        "storage": "N/A",
        "price": 15990.0,
        "platform": "electroplanet",
        "original_name": "SAMSUNG GALAXY S26ULTRA 12+512...",
        "timestamp": "2026-03-28T23:35:21.463753"
    },
    {
        "brand": "Iphone",
        "model": "APPLE  AIR  SKY B",
        "storage": "256GB",
        "price": 17199.0,
        "platform": "electroplanet",
        "original_name": "APPLE IPHONE AIR 256GB SKY B...",
        "timestamp": "2026-03-28T23:36:01.691683"
    },
    {
        "brand": "Iphone",
        "model": "APPLE  AIR  SPACE",
        "storage": "256GB",
        "price": 17199.0,
        "platform": "electroplanet",
        "original_name": "APPLE IPHONE AIR 256GB SPACE...",
        "timestamp": "2026-03-28T23:36:01.749215"
    },
    {
        "brand": "Iphone",
        "model": "APPLE  17 PRO MAX 256G",
        "storage": "N/A",
        "price": 17398.0,
        "platform": "electroplanet",
        "original_name": "APPLE IPHONE 17 PRO MAX 256G...",
        "timestamp": "2026-03-28T23:36:01.257800"
    },
    {
        "brand": "Samsung",
        "model": "Memory Card Micro SD Carte Mémoire Micro SDXC Classe 10  130MBs",
        "storage": "128GB",
        "price": 17500.0,
        "platform": "jumia",
        "original_name": "Samsung Memory Card Micro SD Carte Mémoire Micro SDXC Classe 10 128 GB 130MB/s",
        "timestamp": "2026-03-28T23:34:49.506999"
    },
    {
        "brand": "Samsung",
        "model": "DK101 sans fil écouteur tooth Mini écouteurs pour iPhone Xiaomi",
        "storage": "N/A",
        "price": 17900.0,
        "platform": "jumia",
        "original_name": "DK101 sans fil écouteur Bluetooth Mini écouteurs pour iPhone Xiaomi Samsung",
        "timestamp": "2026-03-28T23:34:50.578483"
    },
    {
        "brand": "Iphone",
        "model": "APPLE  17 PRO  DE",
        "storage": "256GB",
        "price": 18599.0,
        "platform": "electroplanet",
        "original_name": "APPLE IPHONE 17 PRO 256GB DE...",
        "timestamp": "2026-03-28T23:36:01.585870"
    },
    {
        "brand": "Iphone",
        "model": "APPLE  17 PRO  CO",
        "storage": "256GB",
        "price": 18599.0,
        "platform": "electroplanet",
        "original_name": "APPLE IPHONE 17 PRO 256GB CO...",
        "timestamp": "2026-03-28T23:36:01.638271"
    },
    {
        "brand": "Iphone",
        "model": "APPLE  16 PRO  WH",
        "storage": "256GB",
        "price": 18779.0,
        "platform": "electroplanet",
        "original_name": "APPLE IPHONE 16 PRO 256GB WH...",
        "timestamp": "2026-03-28T23:36:02.009568"
    },
    {
        "brand": "Iphone",
        "model": "APPLE  16 PRO  DE",
        "storage": "256GB",
        "price": 18779.0,
        "platform": "electroplanet",
        "original_name": "APPLE IPHONE 16 PRO 256GB DE...",
        "timestamp": "2026-03-28T23:36:02.205392"
    },
    {
        "brand": "Iphone",
        "model": "APPLE  17 PRO MAX 256G",
        "storage": "N/A",
        "price": 20299.0,
        "platform": "electroplanet",
        "original_name": "APPLE IPHONE 17 PRO MAX 256G...",
        "timestamp": "2026-03-28T23:36:01.412754"
    },
    {
        "brand": "Iphone",
        "model": "APPLE  17 PRO MAX 512G",
        "storage": "N/A",
        "price": 24299.0,
        "platform": "electroplanet",
        "original_name": "APPLE IPHONE 17 PRO MAX 512G...",
        "timestamp": "2026-03-28T23:36:01.790097"
    },
    {
        "brand": "Samsung",
        "model": "A07  67     Ram",
        "storage": "64GB",
        "price": 94900.0,
        "platform": "jumia",
        "original_name": "Samsung A07 – 6,7\" – 64 Go – 4 Go Ram – Black",
        "timestamp": "2026-03-28T23:34:49.504575"
    },
    {
        "brand": "Samsung",
        "model": "A07  67   +  Ram  Violet",
        "storage": "64GB",
        "price": 94900.0,
        "platform": "jumia",
        "original_name": "Samsung A07 – 6,7\" – 64 GB + 4 GB Ram – Violet",
        "timestamp": "2026-03-28T23:34:49.504678"
    },
    {
        "brand": "Samsung",
        "model": "A07  67   +  Ram  Green",
        "storage": "64GB",
        "price": 94900.0,
        "platform": "jumia",
        "original_name": "Samsung A07 – 6,7\" – 64 GB + 4 GB Ram – Green",
        "timestamp": "2026-03-28T23:34:49.504778"
    },
    {
        "brand": "Samsung",
        "model": "Galaxy A07  67     RAM  Helio G99  5000 mAh25W  50MP",
        "storage": "64GB",
        "price": 104900.0,
        "platform": "jumia",
        "original_name": "Samsung Galaxy A07 – 6.7\" – 64 Go – 4 Go RAM – Helio G99 – 5000 mAh/25W – 50MP – Noir",
        "timestamp": "2026-03-28T23:34:49.505436"
    },
    {
        "brand": "Samsung",
        "model": "Galaxy A07  67     RAM  Helio G99  5000 mAh25W  50MP  Vert",
        "storage": "64GB",
        "price": 104900.0,
        "platform": "jumia",
        "original_name": "Samsung Galaxy A07 – 6.7\" – 64 Go – 4 Go RAM – Helio G99 – 5000 mAh/25W – 50MP – Vert",
        "timestamp": "2026-03-28T23:34:50.578656"
    },
    {
        "brand": "Samsung",
        "model": "Galaxy A07  67     RAM  Helio G99  5000 mAh25W  50MP + Adapter",
        "storage": "64GB",
        "price": 109900.0,
        "platform": "jumia",
        "original_name": "Samsung Galaxy A07 – 6.7\" – 64 Go – 4 Go RAM – Helio G99 – 5000 mAh/25W – 50MP + Adapter – Noir",
        "timestamp": "2026-03-28T23:34:50.578190"
    },
    {
        "brand": "Samsung",
        "model": "Galaxy A06  67     RAM",
        "storage": "128GB",
        "price": 112900.0,
        "platform": "jumia",
        "original_name": "Samsung Galaxy A06 - 6,7\" - 128 Go - 6 Go RAM – Noir",
        "timestamp": "2026-03-28T23:34:49.504110"
    },
    {
        "brand": "Samsung",
        "model": "Galaxy A06  67     RAM  Light",
        "storage": "128GB",
        "price": 112900.0,
        "platform": "jumia",
        "original_name": "Samsung Galaxy A06 - 6,7\" - 128 Go - 6 Go RAM – Light Blue",
        "timestamp": "2026-03-28T23:34:49.504234"
    },
    {
        "brand": "Samsung",
        "model": "Galaxy A07  67     RAM  Helio G99  5000 mAh25W  50MP + Adapter",
        "storage": "128GB",
        "price": 122900.0,
        "platform": "jumia",
        "original_name": "Samsung Galaxy A07 – 6.7\" – 128 Go – 4 Go RAM – Helio G99 – 5000 mAh/25W – 50MP + Adapter – Noir",
        "timestamp": "2026-03-28T23:34:50.577608"
    },
    {
        "brand": "Samsung",
        "model": "Galaxy A07  67     RAM  Helio G99  5000 mAh25W  50MP  Vert",
        "storage": "128GB",
        "price": 124900.0,
        "platform": "jumia",
        "original_name": "Samsung Galaxy A07 – 6.7\" – 128 Go – 4 Go RAM – Helio G99 – 5000 mAh/25W – 50MP – Vert",
        "timestamp": "2026-03-28T23:34:49.505703"
    },
    {
        "brand": "Samsung",
        "model": "Galaxy A07  67     RAM  Helio G99  5000 mAh25W  50MP  Light Violet",
        "storage": "128GB",
        "price": 124900.0,
        "platform": "jumia",
        "original_name": "Samsung Galaxy A07 – 6.7\" – 128 Go – 4 Go RAM – Helio G99 – 5000 mAh/25W – 50MP – Light Violet",
        "timestamp": "2026-03-28T23:34:49.506482"
    },
    {
        "brand": "Samsung",
        "model": "Galaxy A07  67     RAM  Helio G99  5000 mAh25W  50MP",
        "storage": "128GB",
        "price": 124900.0,
        "platform": "jumia",
        "original_name": "Samsung Galaxy A07 – 6.7\" – 128 Go – 4 Go RAM – Helio G99 – 5000 mAh/25W – 50MP – Noir",
        "timestamp": "2026-03-28T23:34:50.577000"
    },
    {
        "brand": "Samsung",
        "model": "GALAXY A16 128   67",
        "storage": "4GB",
        "price": 144900.0,
        "platform": "jumia",
        "original_name": "Samsung GALAXY A16 128- 4 GB - 6.7\"  black",
        "timestamp": "2026-03-28T23:34:50.576802"
    },
    {
        "brand": "Samsung",
        "model": "A16 67    Amoled 90Hz  Helio G99  5000mAh25W  Light Green",
        "storage": "128GB",
        "price": 152900.0,
        "platform": "jumia",
        "original_name": "Samsung A16 6.7\" (128 Go - 4 Go) Amoled 90Hz - Helio G99 - 5000mAh/25W - Light Green",
        "timestamp": "2026-03-28T23:34:49.506275"
    },
    {
        "brand": "Samsung",
        "model": "A16 67    Amoled 90Hz  Helio G99  5000mAh25W",
        "storage": "128GB",
        "price": 152900.0,
        "platform": "jumia",
        "original_name": "Samsung A16 6.7\" (128 Go - 4 Go) Amoled 90Hz - Helio G99 - 5000mAh/25W - Noir",
        "timestamp": "2026-03-28T23:34:50.579166"
    },
    {
        "brand": "Samsung",
        "model": "Smartphone Galaxy A16   Ram      50Mp Grey",
        "storage": "4GB",
        "price": 158800.0,
        "platform": "jumia",
        "original_name": "Samsung Smartphone Galaxy A16 4G Dual Sim Ram 4GB  - 128 GB  50Mp- Grey",
        "timestamp": "2026-03-28T23:34:50.577517"
    },
    {
        "brand": "Samsung",
        "model": "Smartphone Galaxy A16   Ram      50Mp",
        "storage": "4GB",
        "price": 158900.0,
        "platform": "jumia",
        "original_name": "Samsung Smartphone Galaxy A16 4G Dual Sim Ram 4GB  - 128 GB  50Mp- Black",
        "timestamp": "2026-03-28T23:34:49.506819"
    },
    {
        "brand": "Samsung",
        "model": "A17 67   Ram +     2 ans de garantie",
        "storage": "4GB",
        "price": 169900.0,
        "platform": "jumia",
        "original_name": "Samsung A17 6,7’ 5G 4Go Ram + 128Go – Black - 2 ans de garantie",
        "timestamp": "2026-03-28T23:34:50.577884"
    },
    {
        "brand": "Samsung",
        "model": "Galaxy A14  66     RAM",
        "storage": "128GB",
        "price": 170000.0,
        "platform": "jumia",
        "original_name": "Samsung Galaxy A14 – 6,6\" – 128 Go – 4 Go RAM – Noir",
        "timestamp": "2026-03-28T23:34:49.504378"
    },
    {
        "brand": "Samsung",
        "model": "A07    RAM  Stockage Écran AMOLED 67 Caméra 50 MP Batterie 5000 mAh",
        "storage": "4GB",
        "price": 175500.0,
        "platform": "jumia",
        "original_name": "Samsung A07 Noir – 4 Go RAM, 64 Go Stockage Écran AMOLED 6.7\" Caméra 50 MP Batterie 5000 mAh",
        "timestamp": "2026-03-28T23:34:49.506907"
    },
    {
        "brand": "Samsung",
        "model": "A17 67   Ram +   Grey  2 ans de garantie",
        "storage": "4GB",
        "price": 179900.0,
        "platform": "jumia",
        "original_name": "Samsung A17 6,7’ 5G 4Go Ram + 128Go – Grey - 2 ans de garantie",
        "timestamp": "2026-03-28T23:34:49.505536"
    },
    {
        "brand": "Samsung",
        "model": "A17 67   Ram +     2 ans de garantie",
        "storage": "4GB",
        "price": 179900.0,
        "platform": "jumia",
        "original_name": "Samsung A17 6,7’ 5G 4Go Ram + 128Go – Black - 2 ans de garantie",
        "timestamp": "2026-03-28T23:34:49.505842"
    },
    {
        "brand": "Samsung",
        "model": "A17 67    Amoled 90Hz  Helio G99  5000mAh25W",
        "storage": "128GB",
        "price": 189900.0,
        "platform": "jumia",
        "original_name": "Samsung A17 6.7\" (128 Go - 4 Go) Amoled 90Hz - Helio G99 - 5000mAh/25W - Black",
        "timestamp": "2026-03-28T23:34:50.578318"
    },
    {
        "brand": "Samsung",
        "model": "Galaxy A16  +     2 ans de garantie",
        "storage": "8GB",
        "price": 197900.0,
        "platform": "jumia",
        "original_name": "Samsung Galaxy A16 8GB + 256GB - Black - 2 ans de garantie",
        "timestamp": "2026-03-28T23:34:49.504918"
    },
    {
        "brand": "Samsung",
        "model": "Galaxy A16  +   Gray  2 ans de garantie",
        "storage": "8GB",
        "price": 197900.0,
        "platform": "jumia",
        "original_name": "Samsung Galaxy A16 8GB + 256GB - Gray - 2 ans de garantie",
        "timestamp": "2026-03-28T23:34:49.505016"
    },
    {
        "brand": "Samsung",
        "model": "Galaxy A16  +   Light Green  2 ans de garantie",
        "storage": "8GB",
        "price": 197900.0,
        "platform": "jumia",
        "original_name": "Samsung Galaxy A16 8GB + 256GB - Light Green - 2 ans de garantie",
        "timestamp": "2026-03-28T23:34:49.505159"
    },
    {
        "brand": "Samsung",
        "model": "A17 67   Ram +     2 ans de garantie",
        "storage": "8GB",
        "price": 237900.0,
        "platform": "jumia",
        "original_name": "Samsung A17 6,7’ 5G 8Go Ram + 256 Go – Bleu - 2 ans de garantie",
        "timestamp": "2026-03-28T23:34:49.505302"
    },
    {
        "brand": "Samsung",
        "model": "Galaxy A17  Smartphone    RAM +  ROM  Écran Super AMOLED 65  Batterie 5000 mAh  Double SIM",
        "storage": "8GB",
        "price": 313900.0,
        "platform": "jumia",
        "original_name": "Samsung Galaxy A17 – Smartphone 4G – 8 Go RAM + 256 Go ROM – Écran Super AMOLED 6,5\" – Batterie 5000 mAh – Double SIM",
        "timestamp": "2026-03-28T23:34:50.577795"
    },
    {
        "brand": "Samsung",
        "model": "Galaxy A36   67     50MP+12MP+5MP+32MP + Adapteur Rapide 25W Inclus",
        "storage": "8GB",
        "price": 346900.0,
        "platform": "jumia",
        "original_name": "Samsung  Galaxy A36 5G - 6.7'' - (8GB - 256 GB) -50MP+12MP+5MP+/32MP -Noir+ Adapteur Rapide 25W Inclus",
        "timestamp": "2026-03-28T23:34:49.506146"
    },
    {
        "brand": "Iphone",
        "model": "Apple  XR 61  +  Stockage  Blanc  Remis à Neuf",
        "storage": "64GB",
        "price": 369900.0,
        "platform": "jumia",
        "original_name": "Apple iPhone XR, 6.1\", 64Go + 3Gb Stockage - Blanc - Remis à Neuf",
        "timestamp": "2026-03-28T23:35:33.030642"
    },
    {
        "brand": "Samsung",
        "model": "smartphone Galaxy A56  stockage  Ram  67 Super AMOLED 120 Hz 50+12+5 MPawesome lightgray",
        "storage": "256GB",
        "price": 399600.0,
        "platform": "jumia",
        "original_name": "Samsung smartphone Galaxy A56 5G stockage 256GB Ram 8 GB 6,7 Super AMOLED 120 Hz 50+12+5 MP-awesome lightgray",
        "timestamp": "2026-03-28T23:34:49.505967"
    },
    {
        "brand": "Samsung",
        "model": "smartphone Galaxy A56  stockage  Ram  67 Super AMOLED 120 Hz 50+12+5 MPawesome graphite",
        "storage": "256GB",
        "price": 399800.0,
        "platform": "jumia",
        "original_name": "Samsung smartphone Galaxy A56 5G stockage 256GB Ram 8 GB 6,7 Super AMOLED 120 Hz 50+12+5 MP-awesome graphite",
        "timestamp": "2026-03-28T23:34:49.506732"
    },
    {
        "brand": "Samsung",
        "model": "Galaxy S23 Normal Crème    61 pouces AMOLED 120 Hz Remis à Neuf",
        "storage": "8GB",
        "price": 430000.0,
        "platform": "jumia",
        "original_name": "Samsung Galaxy S23 Normal Crème 8 Go / 256 Go 6.1 pouces AMOLED 120 Hz Remis à Neuf",
        "timestamp": "2026-03-28T23:34:50.578055"
    },
    {
        "brand": "Samsung",
        "model": "Galaxy S23 Normal  61inch  Violet      Remis à Neuf",
        "storage": "8GB",
        "price": 435900.0,
        "platform": "jumia",
        "original_name": "Samsung Galaxy S23 Normal - 6.1-inch - Violet - 8 GB / 256 GB - Remis à Neuf",
        "timestamp": "2026-03-28T23:34:50.578745"
    },
    {
        "brand": "Iphone",
        "model": "Apple  12 Pro    RAM Remis à neuf Garantie 6 mois graphite",
        "storage": "256GB",
        "price": 469900.0,
        "platform": "jumia",
        "original_name": "Apple iPhone 12 Pro 256Go , 6Gb RAM Remis à neuf Garantie 6 mois, graphite bleu",
        "timestamp": "2026-03-28T23:35:33.031326"
    },
    {
        "brand": "Iphone",
        "model": "Apple  14   +  RAM  Midnight  Ecran XDR OLED 61  A15 Bionic  Remis a neuf",
        "storage": "128GB",
        "price": 499900.0,
        "platform": "jumia",
        "original_name": "Apple iPhone 14 5G 128 Go + 6 Go RAM - Midnight - Ecran XDR OLED 6.1\" - A15 Bionic - Remis a neuf",
        "timestamp": "2026-03-28T23:35:34.395262"
    },
    {
        "brand": "Iphone",
        "model": "Apple  13 Pro      Graphite  61inch  Remis à neuf",
        "storage": "256GB",
        "price": 575000.0,
        "platform": "jumia",
        "original_name": "Apple iPhone 13 Pro - 256GB - Noir / Graphite - 6.1-inch - Remis à neuf",
        "timestamp": "2026-03-28T23:35:33.028092"
    },
    {
        "brand": "Iphone",
        "model": "Apple  16e    RAM 48 Mpx 61 Puce A18 iOS Bouton Action Ecran Super Retina XDR OLED 61 1170 x 2532",
        "storage": "128GB",
        "price": 575000.0,
        "platform": "jumia",
        "original_name": "Apple iPhone 16e 128 Go Black 8 Go RAM 48 Mpx 6.1 Puce A18 iOS Bouton Action Ecran Super Retina XDR OLED 6.1\" 1170 x 2532 5G",
        "timestamp": "2026-03-28T23:35:34.395128"
    },
    {
        "brand": "Iphone",
        "model": "Apple  13 Pro     Alpin  61inch  Remis à neuf",
        "storage": "256GB",
        "price": 580000.0,
        "platform": "jumia",
        "original_name": "Apple iPhone 13 Pro - 256GB - Bleu Alpin - 6.1-inch - Remis à neuf",
        "timestamp": "2026-03-28T23:35:33.029552"
    },
    {
        "brand": "Iphone",
        "model": "Apple  13 Pro    Vert Alpin  61inch  Remis à neuf",
        "storage": "256GB",
        "price": 580000.0,
        "platform": "jumia",
        "original_name": "Apple iPhone 13 Pro - 256GB - Vert Alpin - 6.1-inch - Remis à neuf",
        "timestamp": "2026-03-28T23:35:34.394945"
    },
    {
        "brand": "Iphone",
        "model": "Apple  13  61     RAM  Minuit",
        "storage": "128GB",
        "price": 597500.0,
        "platform": "jumia",
        "original_name": "Apple iPhone 13 – 6,1\" – 128 Go – 4 Go RAM – Minuit",
        "timestamp": "2026-03-28T23:35:33.028796"
    },
    {
        "brand": "Iphone",
        "model": "Apple  16e    RAM 48 Mpx 61 Puce A18 iOS Bouton Action",
        "storage": "128GB",
        "price": 647500.0,
        "platform": "jumia",
        "original_name": "Apple iPhone 16e 128 Go Noir 8 Go RAM 48 Mpx 6.1 Puce A18 iOS Bouton Action 5G",
        "timestamp": "2026-03-28T23:35:33.028979"
    },
    {
        "brand": "Iphone",
        "model": "Apple  16e  Blanc  RAM 48 Mpx 61 Puce A18 iOS Bouton Action",
        "storage": "128GB",
        "price": 647500.0,
        "platform": "jumia",
        "original_name": "Apple iPhone 16e 128 Go Blanc 8 Go RAM 48 Mpx 6.1 Puce A18 iOS Bouton Action 5G",
        "timestamp": "2026-03-28T23:35:34.396219"
    },
    {
        "brand": "Iphone",
        "model": "Apple  13  61     RAM  Lumière Stellaire",
        "storage": "128GB",
        "price": 647500.0,
        "platform": "jumia",
        "original_name": "Apple iPhone 13 – 6,1\" – 128 Go – 4 Go RAM – Lumière Stellaire",
        "timestamp": "2026-03-28T23:35:34.397158"
    },
    {
        "brand": "Iphone",
        "model": "Apple  13 Pro Max  67        Remis à neuf",
        "storage": "128GB",
        "price": 659900.0,
        "platform": "jumia",
        "original_name": "Apple iPhone 13 Pro Max - 6.7\" - 128 Go - 6GB - Gold - Remis à neuf",
        "timestamp": "2026-03-28T23:35:33.030001"
    },
    {
        "brand": "Samsung",
        "model": "Galaxy S23 Ultra Crème     Remis à Neuf",
        "storage": "12GB",
        "price": 685000.0,
        "platform": "jumia",
        "original_name": "Samsung Galaxy S23 Ultra Crème 12 Go / 256 Go - Remis à Neuf",
        "timestamp": "2026-03-28T23:34:50.577390"
    },
    {
        "brand": "Iphone",
        "model": "Apple  14  61     RAM  Minuit  Bionic A15",
        "storage": "128GB",
        "price": 699900.0,
        "platform": "jumia",
        "original_name": "Apple iPhone 14 – 6.1\" – 128 Go – 6 Go RAM - Minuit – Bionic A15",
        "timestamp": "2026-03-28T23:35:34.396626"
    },
    {
        "brand": "Iphone",
        "model": "Apple  14 Plus Violet   Mauve 67 pouces A15 IOS Neuf",
        "storage": "256GB",
        "price": 759900.0,
        "platform": "jumia",
        "original_name": "Apple iPhone 14 Plus Violet 256 Go, 6 Go Mauve 6,7 pouces A15 IOS Neuf",
        "timestamp": "2026-03-28T23:35:34.394760"
    },
    {
        "brand": "Iphone",
        "model": "Apple  15  61     RAM  Pink",
        "storage": "128GB",
        "price": 787500.0,
        "platform": "jumia",
        "original_name": "Apple iPhone 15 – 6,1\" – 128 Go – 6 Go RAM – Pink",
        "timestamp": "2026-03-28T23:35:33.028516"
    },
    {
        "brand": "Iphone",
        "model": "Apple  15  61     RAM",
        "storage": "128GB",
        "price": 797500.0,
        "platform": "jumia",
        "original_name": "Apple iPhone 15 – 6,1\" – 128 Go – 6 Go RAM – Bleu",
        "timestamp": "2026-03-28T23:35:33.028369"
    },
    {
        "brand": "Iphone",
        "model": "Apple  15  61     RAM",
        "storage": "128GB",
        "price": 797500.0,
        "platform": "jumia",
        "original_name": "Apple iPhone 15 – 6,1\" – 128 Go – 6 Go RAM – Noir",
        "timestamp": "2026-03-28T23:35:33.030101"
    },
    {
        "brand": "Iphone",
        "model": "Apple  15  Rose Pink Dynamic Island  Retina XDR OLED 61  RAM  New",
        "storage": "128GB",
        "price": 799900.0,
        "platform": "jumia",
        "original_name": "Apple iPhone 15 128 GB (Rose) Pink Dynamic Island - Retina XDR OLED 6.1\" 6GB RAM - New",
        "timestamp": "2026-03-28T23:35:34.395712"
    },
    {
        "brand": "Iphone",
        "model": "Apple  16  61     RAM",
        "storage": "128GB",
        "price": 857500.0,
        "platform": "jumia",
        "original_name": "Apple iPhone 16 – 6,1\" – 128 Go – 8 Go RAM – Noir",
        "timestamp": "2026-03-28T23:35:34.394472"
    },
    {
        "brand": "Samsung",
        "model": "Galaxy Z Flip7  Coral Rouge  69inch  41inch      Neuf",
        "storage": "12GB",
        "price": 870000.0,
        "platform": "jumia",
        "original_name": "Samsung Galaxy Z Flip7 - Coral Rouge - 6.9-inch / 4.1-inch - 12 GB / 256 GB - Neuf",
        "timestamp": "2026-03-28T23:34:50.577704"
    },
    {
        "brand": "Samsung",
        "model": "Galaxy S24 Ultra      Titanium   Remis à Neuf",
        "storage": "12GB",
        "price": 879900.0,
        "platform": "jumia",
        "original_name": "Samsung Galaxy S24 Ultra 5G 12GB / 512GB Bleu (Titanium Blue) - Remis à Neuf",
        "timestamp": "2026-03-28T23:34:50.579038"
    },
    {
        "brand": "Iphone",
        "model": "Apple  16  61     RAM  Outremer",
        "storage": "128GB",
        "price": 897500.0,
        "platform": "jumia",
        "original_name": "Apple iPhone 16 – 6,1\" – 128 Go – 8 Go RAM – Outremer",
        "timestamp": "2026-03-28T23:35:33.030919"
    },
    {
        "brand": "Iphone",
        "model": "Apple  16  61     RAM  Sarcelle",
        "storage": "128GB",
        "price": 897500.0,
        "platform": "jumia",
        "original_name": "Apple iPhone 16 – 6,1\" – 128 Go – 8 Go RAM – Sarcelle",
        "timestamp": "2026-03-28T23:35:34.395037"
    },
    {
        "brand": "Iphone",
        "model": "Apple  16  61     RAM  Blanc",
        "storage": "128GB",
        "price": 897500.0,
        "platform": "jumia",
        "original_name": "Apple iPhone 16 – 6,1\" – 128 Go – 8 Go RAM – Blanc",
        "timestamp": "2026-03-28T23:35:34.396979"
    },
    {
        "brand": "Iphone",
        "model": "APPLE  16",
        "storage": "N/A",
        "price": 899000.0,
        "platform": "electroplanet",
        "original_name": "APPLE IPHONE 16",
        "timestamp": "2026-03-28T23:36:01.882347"
    },
    {
        "brand": "Samsung",
        "model": "Smartphone Galaxy S24FE  67  Ram  stockage Graphite",
        "storage": "8GB",
        "price": 899900.0,
        "platform": "jumia",
        "original_name": "Samsung Smartphone Galaxy S24FE Dual Sim 6,7\"  Ram 8GB stockage 256 GB-Graphite",
        "timestamp": "2026-03-28T23:34:49.506569"
    },
    {
        "brand": "Iphone",
        "model": "Apple  16  61     RAM  Rose",
        "storage": "128GB",
        "price": 917500.0,
        "platform": "jumia",
        "original_name": "Apple iPhone 16 – 6,1\" – 128 Go – 8 Go RAM – Rose",
        "timestamp": "2026-03-28T23:35:33.028888"
    },
    {
        "brand": "Samsung",
        "model": "Galaxy S24 Ultra SMS928B  68     RAM  Dynamic AMOLED 2x  Titanium   Neuf",
        "storage": "256GB",
        "price": 997500.0,
        "platform": "jumia",
        "original_name": "Samsung Galaxy S24 Ultra SM-S928B – 6.8\" – 256 Go – 12 Go RAM – Dynamic AMOLED 2x – Titanium Noir – Neuf",
        "timestamp": "2026-03-28T23:34:50.576905"
    },
    {
        "brand": "Iphone",
        "model": "Apple  15 Pro Max  67inch    Titane   Remis à Neuf",
        "storage": "1TB",
        "price": 999900.0,
        "platform": "jumia",
        "original_name": "Apple iPhone 15 Pro Max - 6.7-inch - 1TB - Titane Bleu - Remis à Neuf",
        "timestamp": "2026-03-28T23:35:34.394853"
    },
    {
        "brand": "Iphone",
        "model": "Apple  17   RAM 63 Puce A19  iOS 48 Mpx",
        "storage": "256GB",
        "price": 1017500.0,
        "platform": "jumia",
        "original_name": "Apple iPhone 17 256 Go 8 Go RAM 6,3\" Puce A19 Noir iOS 48 Mpx",
        "timestamp": "2026-03-28T23:35:34.397379"
    },
    {
        "brand": "Iphone",
        "model": "Apple  17 Normal  63inch  Neuf",
        "storage": "256GB",
        "price": 1019900.0,
        "platform": "jumia",
        "original_name": "Apple iPhone 17 Normal 256 GB 6.3-inch bleu Neuf",
        "timestamp": "2026-03-28T23:35:34.397508"
    },
    {
        "brand": "Iphone",
        "model": "Apple  17 Normal  63inch  Neuf",
        "storage": "256GB",
        "price": 1024900.0,
        "platform": "jumia",
        "original_name": "Apple iPhone 17 Normal 256 GB 6.3-inch Noir Neuf",
        "timestamp": "2026-03-28T23:35:34.394670"
    },
    {
        "brand": "Iphone",
        "model": "Apple  15 Pro Max   Titane   Ecran OLED 67 inch   RAM  New",
        "storage": "256GB",
        "price": 1040000.0,
        "platform": "jumia",
        "original_name": "Apple iPhone 15 Pro Max 256 Go - Titane Black - Ecran OLED 6.7\" inch - 8 Go RAM - New",
        "timestamp": "2026-03-28T23:35:34.395800"
    },
    {
        "brand": "Iphone",
        "model": "Apple  Air  65  RAM Puce A19 Pro eSIM  Sidéral Titane iOS",
        "storage": "256GB",
        "price": 1067500.0,
        "platform": "jumia",
        "original_name": "Apple iPhone Air 256 Go 6,5\" 12 Go RAM Puce A19 Pro eSIM Noir Sidéral Titane iOS",
        "timestamp": "2026-03-28T23:35:34.396130"
    },
    {
        "brand": "Iphone",
        "model": "Apple  Air   sidéral LTE IP68  A19 Pro HexaCore  Écran Super Retina XDR OLED 65inch 2736 x 1260  WiFi 7tooth 6NFC  iOS 26 Neuf",
        "storage": "256GB",
        "price": 1070000.0,
        "platform": "jumia",
        "original_name": "Apple iPhone Air 256 GB Noir sidéral 5G-LTE IP68 - A19 Pro Hexa-Core - Écran Super Retina XDR OLED 6.5-inch 2736 x 1260 - Wi-Fi 7/Bluetooth 6/NFC - iOS 26 Neuf",
        "timestamp": "2026-03-28T23:35:34.396850"
    },
    {
        "brand": "Iphone",
        "model": "Apple  16 Plus  67     RAM",
        "storage": "128GB",
        "price": 1087500.0,
        "platform": "jumia",
        "original_name": "Apple iPhone 16 Plus – 6,7\" – 128 Go – 8 Go RAM – Noir",
        "timestamp": "2026-03-28T23:35:34.397597"
    },
    {
        "brand": "Iphone",
        "model": "Apple  16 Plus  67     RAM  Rose",
        "storage": "128GB",
        "price": 1097500.0,
        "platform": "jumia",
        "original_name": "Apple iPhone 16 Plus – 6,7\" – 128 Go – 8 Go RAM – Rose",
        "timestamp": "2026-03-28T23:35:34.395624"
    },
    {
        "brand": "Iphone",
        "model": "Apple  Air  65  RAM Puce A19 Pro eSIM Blanc Nuage Titane iOS",
        "storage": "256GB",
        "price": 1127500.0,
        "platform": "jumia",
        "original_name": "Apple iPhone Air 256 Go 6,5\" 12 Go RAM Puce A19 Pro eSIM Blanc Nuage Titane iOS",
        "timestamp": "2026-03-28T23:35:34.396716"
    },
    {
        "brand": "Iphone",
        "model": "Apple  Air    Or clair  65 pouces  iOS 26  Neuf",
        "storage": "256GB",
        "price": 1135500.0,
        "platform": "jumia",
        "original_name": "Apple iPhone Air - 256 Go - Or clair - 6.5 pouces - iOS 26 - Neuf",
        "timestamp": "2026-03-28T23:35:34.397687"
    },
    {
        "brand": "Iphone",
        "model": "Apple  15 Pro Max   Titanium Naturel   RAM Ecran XDR OLED 67  New",
        "storage": "512GB",
        "price": 1139900.0,
        "platform": "jumia",
        "original_name": "Apple iPhone 15 Pro Max 512 Go - Titanium Naturel - 8 Go RAM Ecran XDR OLED 6.7\" - New",
        "timestamp": "2026-03-28T23:35:33.029869"
    },
    {
        "brand": "Iphone",
        "model": "Apple  16 Pro Max  +    Titane  Remis à Neuf",
        "storage": "8GB",
        "price": 1195900.0,
        "platform": "jumia",
        "original_name": "Apple iPhone 16 Pro Max 8GB + 256GB - Noir Titane - Remis à Neuf",
        "timestamp": "2026-03-28T23:35:34.395448"
    },
    {
        "brand": "Iphone",
        "model": "Apple  16 Pro Max    Sable  Désert Titane  Neuf Sans Emballage  Jamais activée",
        "storage": "512GB",
        "price": 1239900.0,
        "platform": "jumia",
        "original_name": "Apple iPhone 16 Pro Max - 512 GB - Sable / Désert Titane - Neuf Sans Emballage - Jamais activée.",
        "timestamp": "2026-03-28T23:35:33.029687"
    },
    {
        "brand": "Iphone",
        "model": "Apple  Air    Or clair  65 pouces  iOS 26 Neuf",
        "storage": "512GB",
        "price": 1309900.0,
        "platform": "jumia",
        "original_name": "Apple iPhone Air - 512 Go - Or clair - 6.5 pouces - iOS 26 Neuf",
        "timestamp": "2026-03-28T23:35:34.397067"
    },
    {
        "brand": "Iphone",
        "model": "Apple  12 Pro Max    RAM Remis à neuf Garantie 6 mois Graphite",
        "storage": "256GB",
        "price": 1399900.0,
        "platform": "jumia",
        "original_name": "Apple iPhone 12 Pro Max 256Go , 6Gb RAM Remis à neuf Garantie 6 mois, Graphite",
        "timestamp": "2026-03-28T23:35:33.031446"
    },
    {
        "brand": "Iphone",
        "model": "Apple  17 Pro  63  RAM Puce A19 Pro Orange Cosmique iOS",
        "storage": "256GB",
        "price": 1467500.0,
        "platform": "jumia",
        "original_name": "Apple iPhone 17 Pro 256 Go 6,3\" 12 Go RAM Puce A19 Pro Orange Cosmique iOS",
        "timestamp": "2026-03-28T23:35:33.029457"
    },
    {
        "brand": "Iphone",
        "model": "Apple  17 Pro  63  RAM Puce A19 Pro  Intense iOS",
        "storage": "256GB",
        "price": 1467500.0,
        "platform": "jumia",
        "original_name": "Apple iPhone 17 Pro 256 Go 6,3\" 12 Go RAM Puce A19 Pro Bleu Intense iOS",
        "timestamp": "2026-03-28T23:35:33.029779"
    },
    {
        "brand": "Iphone",
        "model": "Apple  17 Pro  63  RAM Puce A19 Pro Argent iOS",
        "storage": "256GB",
        "price": 1467500.0,
        "platform": "jumia",
        "original_name": "Apple iPhone 17 Pro 256 Go 6,3\" 12 Go RAM Puce A19 Pro Argent iOS",
        "timestamp": "2026-03-28T23:35:34.394578"
    },
    {
        "brand": "Samsung",
        "model": "Galaxy S26 Ultra   RAM      Neuf",
        "storage": "12GB",
        "price": 1477500.0,
        "platform": "jumia",
        "original_name": "Samsung Galaxy S26 Ultra – 12GB RAM / 512GB - Noir - Neuf",
        "timestamp": "2026-03-28T23:34:50.577175"
    },
    {
        "brand": "Iphone",
        "model": "Apple  17 Pro   Argent  Smartphone LTE IP68  A19 Pro HexaCore  Écran Super Retina XDR OLED 63 pouces 1206 x 2622  NFCtooth 6  iOS 26 Neuf",
        "storage": "256GB",
        "price": 1477500.0,
        "platform": "jumia",
        "original_name": "Apple iPhone 17 Pro 256GB - Argent - Smartphone 5G-LTE IP68 - A19 Pro Hexa-Core - Écran Super Retina XDR OLED 6.3 pouces 1206 x 2622 - NFC/Bluetooth 6 - iOS 26 Neuf",
        "timestamp": "2026-03-28T23:35:33.030545"
    },
    {
        "brand": "Iphone",
        "model": "Apple  17 Pro   Orange Cosmique  Smartphone LTE IP68  A19 Pro HexaCore  Écran Super Retina XDR OLED 63 pouces 1206 x 2622  NFCtooth 6  iOS 26 Neuf",
        "storage": "256GB",
        "price": 1477500.0,
        "platform": "jumia",
        "original_name": "Apple iPhone 17 Pro 256GB - Orange Cosmique - Smartphone 5G-LTE IP68 - A19 Pro Hexa-Core - Écran Super Retina XDR OLED 6.3 pouces 1206 x 2622 - NFC/Bluetooth 6 - iOS 26 Neuf",
        "timestamp": "2026-03-28T23:35:33.031134"
    },
    {
        "brand": "Iphone",
        "model": "Apple  17 Pro    Intense  Smartphone LTE IP68  A19 Pro HexaCore  Écran Super Retina XDR OLED 63 pouces 1206 x 2622  NFCtooth 6  iOS 26 Neuf",
        "storage": "256GB",
        "price": 1477500.0,
        "platform": "jumia",
        "original_name": "Apple iPhone 17 Pro 256GB - Bleu Intense - Smartphone 5G-LTE IP68 - A19 Pro Hexa-Core - Écran Super Retina XDR OLED 6.3 pouces 1206 x 2622 - NFC/Bluetooth 6 - iOS 26 Neuf",
        "timestamp": "2026-03-28T23:35:34.396310"
    },
    {
        "brand": "Iphone",
        "model": "Apple  16 Pro Max  Titane  69 Contrôle de Camera A18 Pro  RAM iOS 18",
        "storage": "512GB",
        "price": 1497500.0,
        "platform": "jumia",
        "original_name": "Apple iPhone 16 Pro Max 512GB Titane Noir 6,9\" Contrôle de Camera A18 Pro 8GB RAM iOS 18",
        "timestamp": "2026-03-28T23:35:33.030191"
    },
    {
        "brand": "Iphone",
        "model": "Apple  17 Pro Max  69  RAM Puce A19 Pro Orange Cosmique iOS",
        "storage": "256GB",
        "price": 1597500.0,
        "platform": "jumia",
        "original_name": "Apple iPhone 17 Pro Max 256 Go 6,9\" 12 Go RAM Puce A19 Pro Orange Cosmique iOS",
        "timestamp": "2026-03-28T23:35:33.027794"
    },
    {
        "brand": "Iphone",
        "model": "Apple  17 Pro Max  69  RAM Puce A19 Pro Argent iOS",
        "storage": "256GB",
        "price": 1597500.0,
        "platform": "jumia",
        "original_name": "Apple iPhone 17 Pro Max 256 Go 6,9\" 12 Go RAM Puce A19 Pro Argent iOS",
        "timestamp": "2026-03-28T23:35:33.027897"
    },
    {
        "brand": "Iphone",
        "model": "Apple  17 Pro Max  69  RAM Puce A19 Pro  Intense iOS",
        "storage": "256GB",
        "price": 1597500.0,
        "platform": "jumia",
        "original_name": "Apple iPhone 17 Pro Max 256 Go 6,9\" 12 Go RAM Puce A19 Pro Bleu Intense iOS",
        "timestamp": "2026-03-28T23:35:33.027992"
    },
    {
        "brand": "Iphone",
        "model": "Apple  17 Pro Max    Argent  Smartphone LTE IP68   A19 Pro HexaCore  Écran Super Retina XDR OLED 69 pouces 1320 x 2868  NFCtooth 6  iOS 26 Neuf",
        "storage": "256GB",
        "price": 1599900.0,
        "platform": "jumia",
        "original_name": "Apple iPhone 17 Pro Max / 256 Go / Argent / Smartphone 5G-LTE IP68 Dual SIM - A19 Pro Hexa-Core - Écran Super Retina XDR OLED 6.9 pouces 1320 x 2868 - NFC/Bluetooth 6 - iOS 26 Neuf",
        "timestamp": "2026-03-28T23:35:33.028611"
    },
    {
        "brand": "Iphone",
        "model": "Apple  17 Pro Max    Orange Cosmique  Smartphone LTE IP68   A19 Pro HexaCore  Écran Super Retina XDR OLED 69inch 1320 x 2868  NFCtooth 6  iOS 26 Neuf",
        "storage": "256GB",
        "price": 1599900.0,
        "platform": "jumia",
        "original_name": "Apple iPhone 17 Pro Max / 256GB / Orange Cosmique / Smartphone 5G-LTE IP68 Dual SIM - A19 Pro Hexa-Core - Écran Super Retina XDR OLED 6.9-inch 1320 x 2868 - NFC/Bluetooth 6 - iOS 26 Neuf",
        "timestamp": "2026-03-28T23:35:33.028705"
    },
    {
        "brand": "Iphone",
        "model": "Apple  17 Pro Max     Intense  Smartphone LTE IP68   A19 Pro HexaCore  Écran Super Retina XDR OLED 69inch 1320 x 2868  NFCtooth 6  iOS 26 Neuf",
        "storage": "256GB",
        "price": 1599900.0,
        "platform": "jumia",
        "original_name": "Apple iPhone 17 Pro Max / 256GB / Bleu Intense / Smartphone 5G-LTE IP68 Dual SIM - A19 Pro Hexa-Core - Écran Super Retina XDR OLED 6.9-inch 1320 x 2868 - NFC/Bluetooth 6 - iOS 26 Neuf",
        "timestamp": "2026-03-28T23:35:34.396402"
    },
    {
        "brand": "Iphone",
        "model": "Apple  17 Pro   Orange Cosmique  Smartphone LTE IP68  A19 Pro HexaCore  Écran Super Retina XDR OLED 63 pouces 1206 x 2622  NFCtooth 6  iOS 26 Neuf",
        "storage": "512GB",
        "price": 1654900.0,
        "platform": "jumia",
        "original_name": "Apple iPhone 17 Pro 512GB - Orange Cosmique - Smartphone 5G-LTE IP68 - A19 Pro Hexa-Core - Écran Super Retina XDR OLED 6.3 pouces 1206 x 2622 - NFC/Bluetooth 6 - iOS 26 Neuf",
        "timestamp": "2026-03-28T23:35:33.029360"
    },
    {
        "brand": "Iphone",
        "model": "Apple  17 Pro    Intense  Smartphone LTE IP68  A19 Pro HexaCore  Écran Super Retina XDR OLED 63 pouces 1206 x 2622  NFCtooth 6  iOS 26 Neuf",
        "storage": "512GB",
        "price": 1654900.0,
        "platform": "jumia",
        "original_name": "Apple iPhone 17 Pro 512 GB - Bleu Intense - Smartphone 5G-LTE IP68 - A19 Pro Hexa-Core - Écran Super Retina XDR OLED 6.3 pouces 1206 x 2622 - NFC/Bluetooth 6 - iOS 26 Neuf",
        "timestamp": "2026-03-28T23:35:34.395981"
    },
    {
        "brand": "Iphone",
        "model": "Apple  17 Pro   Argent  Smartphone LTE IP68  A19 Pro HexaCore  Écran Super Retina XDR OLED 63 pouces 1206 x 2622  NFCtooth 6  iOS 26 Neuf",
        "storage": "512GB",
        "price": 1654900.0,
        "platform": "jumia",
        "original_name": "Apple iPhone 17 Pro 512GB - Argent - Smartphone 5G-LTE IP68 - A19 Pro Hexa-Core - Écran Super Retina XDR OLED 6.3 pouces 1206 x 2622 - NFC/Bluetooth 6 - iOS 26 Neuf",
        "timestamp": "2026-03-28T23:35:34.397292"
    },
    {
        "brand": "Iphone",
        "model": "APPLE  16 PRO",
        "storage": "N/A",
        "price": 1689900.0,
        "platform": "electroplanet",
        "original_name": "APPLE IPHONE 16 PRO",
        "timestamp": "2026-03-28T23:36:01.830851"
    },
    {
        "brand": "Iphone",
        "model": "Apple  17 Pro  63  RAM Puce A19 Pro Orange Cosmique iOS",
        "storage": "512GB",
        "price": 1697500.0,
        "platform": "jumia",
        "original_name": "Apple iPhone 17 Pro 512 Go 6,3\" 12 Go RAM Puce A19 Pro Orange Cosmique iOS",
        "timestamp": "2026-03-28T23:35:34.395890"
    },
    {
        "brand": "Iphone",
        "model": "Apple  17 Pro  63  RAM Puce A19 Pro Argent iOS",
        "storage": "512GB",
        "price": 1697500.0,
        "platform": "jumia",
        "original_name": "Apple iPhone 17 Pro 512 Go 6,3\" 12 Go RAM Puce A19 Pro Argent iOS",
        "timestamp": "2026-03-28T23:35:34.396532"
    },
    {
        "brand": "Iphone",
        "model": "Apple  17 Pro Max    Orange Cosmique  Smartphone LTE IP68   A19 Pro HexaCore  Écran Super Retina XDR OLED 69inch 1320 x 2868  NFCtooth 6  iOS 26 Neuf",
        "storage": "512GB",
        "price": 1927500.0,
        "platform": "jumia",
        "original_name": "Apple iPhone 17 Pro Max / 512GB / Orange Cosmique / Smartphone 5G-LTE IP68 Dual SIM - A19 Pro Hexa-Core - Écran Super Retina XDR OLED 6.9-inch 1320 x 2868 - NFC/Bluetooth 6 - iOS 26 Neuf",
        "timestamp": "2026-03-28T23:35:33.029167"
    },
    {
        "brand": "Iphone",
        "model": "Apple  17 Pro Max    Argent  Smartphone LTE IP68   A19 Pro HexaCore  Écran Super Retina XDR OLED 69 pouces 1320 x 2868  NFCtooth 6  iOS 26 Neuf",
        "storage": "512GB",
        "price": 1927500.0,
        "platform": "jumia",
        "original_name": "Apple iPhone 17 Pro Max / 512 Go / Argent / Smartphone 5G-LTE IP68 Dual SIM - A19 Pro Hexa-Core - Écran Super Retina XDR OLED 6.9 pouces 1320 x 2868 - NFC/Bluetooth 6 - iOS 26 Neuf",
        "timestamp": "2026-03-28T23:35:33.030321"
    },
    {
        "brand": "Iphone",
        "model": "Apple  17 Pro Max     Intense  Smartphone LTE IP68   A19 Pro HexaCore  Écran Super Retina XDR OLED 69inch 1320 x 2868  NFCtooth 6  iOS 26 Neuf",
        "storage": "512GB",
        "price": 1927500.0,
        "platform": "jumia",
        "original_name": "Apple iPhone 17 Pro Max / 512GB / Bleu Intense / Smartphone 5G-LTE IP68 Dual SIM - A19 Pro Hexa-Core - Écran Super Retina XDR OLED 6.9-inch 1320 x 2868 - NFC/Bluetooth 6 - iOS 26 Neuf",
        "timestamp": "2026-03-28T23:35:33.030436"
    },
    {
        "brand": "Iphone",
        "model": "Apple  17 Pro Max  69  RAM Puce A19 Pro Orange Cosmique iOS",
        "storage": "512GB",
        "price": 1947500.0,
        "platform": "jumia",
        "original_name": "Apple iPhone 17 Pro Max 512 Go 6,9\" 12 Go RAM Puce A19 Pro Orange Cosmique iOS",
        "timestamp": "2026-03-28T23:35:33.028277"
    },
    {
        "brand": "Iphone",
        "model": "Apple  17 Pro Max  69  RAM Puce A19 Pro Argent iOS",
        "storage": "512GB",
        "price": 1947500.0,
        "platform": "jumia",
        "original_name": "Apple iPhone 17 Pro Max 512 Go 6,9\" 12 Go RAM Puce A19 Pro Argent iOS",
        "timestamp": "2026-03-28T23:35:33.029264"
    },
    {
        "brand": "Iphone",
        "model": "Apple  17 Pro Max  69  RAM Puce A19 Pro  Intense iOS",
        "storage": "512GB",
        "price": 1947500.0,
        "platform": "jumia",
        "original_name": "Apple iPhone 17 Pro Max 512 Go 6,9\" 12 Go RAM Puce A19 Pro Bleu Intense iOS",
        "timestamp": "2026-03-28T23:35:33.030798"
    }
]